{"name":"the categories tab is present","id":"buy-a-product-in-the-falabella-application;the-categories-tab-is-present","testSteps":[{"number":1,"description":"Given the user is in the falabella application","duration":6192,"startTime":"2022-04-16T21:54:49.152-05:00[America/Bogota]","screenshots":[{"screenshot":"e91dd9dbd7694096ed64d6c640dba5fc2cc28267beed6a80441c91325f81b346.png","timeStamp":1650164095344}],"result":"SUCCESS","precondition":false,"level":0,"children":[{"number":2,"description":"Juan open browser","duration":6018,"startTime":"2022-04-16T21:54:49.325-05:00[America/Bogota]","screenshots":[{"screenshot":"e91dd9dbd7694096ed64d6c640dba5fc2cc28267beed6a80441c91325f81b346.png","timeStamp":1650164095343}],"result":"SUCCESS","precondition":false,"level":1,"children":[{"number":3,"description":"Juan opens the Falabella page","duration":5982,"startTime":"2022-04-16T21:54:49.340-05:00[America/Bogota]","screenshots":[{"screenshot":"e91dd9dbd7694096ed64d6c640dba5fc2cc28267beed6a80441c91325f81b346.png","timeStamp":1650164095321}],"result":"SUCCESS","precondition":false,"level":2}]}]},{"number":4,"description":"Then the user should see the button Categorías","duration":1617,"startTime":"2022-04-16T21:54:55.344-05:00[America/Bogota]","screenshots":[{"screenshot":"e91dd9dbd7694096ed64d6c640dba5fc2cc28267beed6a80441c91325f81b346.png","timeStamp":1650164096961}],"result":"SUCCESS","precondition":false,"level":0,"children":[{"number":5,"description":"Then validate option categoria","duration":1545,"startTime":"2022-04-16T21:54:55.415-05:00[America/Bogota]","screenshots":[{"screenshot":"e91dd9dbd7694096ed64d6c640dba5fc2cc28267beed6a80441c91325f81b346.png","timeStamp":1650164096959}],"result":"SUCCESS","precondition":false,"level":1}]}],"userStory":{"id":"buy-a-product-in-the-falabella-application","storyName":"buy a product in the falabella application","path":"src/test/resources/features/product_shopping_bag.feacture","type":"feature"},"featureTag":{"name":"Feacture/buy a product in the falabella application","type":"feature","displayName":"Feacture/buy a product in the falabella application"},"title":"the categories tab is present","tags":[{"name":"Smoke","type":"tag","displayName":"Smoke"}],"startTime":"2022-04-16T21:54:49.046-05:00[America/Bogota]","duration":7916,"projectKey":"","sessionId":"8b2bde6128bac2e4cee038e87dc73526","driver":"chrome:juan","manual":false,"testSource":"Cucumber","actors":[{"name":"Juan","can":["browse the web"]}],"result":"SUCCESS"}